captain/__init__.py
captain/call.py
captain/compat.py
captain/config.py
captain/decorators.py
captain/exception.py
captain/interface.py
captain/io.py
captain/logging.py
captain/parse.py
captain/reflection.py
captain-6.0.0.dist-info/licenses/LICENSE.txt
captain-6.0.0.dist-info/METADATA
captain-6.0.0.dist-info/WHEEL
captain-6.0.0.dist-info/top_level.txt
captain-6.0.0.dist-info/RECORD
