Metadata-Version: 2.4
Name: captain
Version: 6.0.0
Summary: Python cli scripts for humans
Author-email: Jay Marcyes <jay@marcyes.com>
License: The MIT License (MIT)
Project-URL: Homepage, http://github.com/jaymon/captain
Project-URL: Repository, https://github.com/Jaymon/captain
Keywords: cli console
Classifier: Development Status :: 5 - Production/Stable
Classifier: Intended Audience :: Developers
Classifier: License :: OSI Approved :: MIT License
Classifier: Operating System :: OS Independent
Classifier: Programming Language :: Python :: 3
Requires-Python: >=3.10
License-File: LICENSE.txt
Requires-Dist: datatypes
Dynamic: license-file
